meridianalgo/__init__.py
meridianalgo/smarttrader/__init__.py
meridianalgo/smarttrader/analysis.py
meridianalgo/smarttrader/cli.py
meridianalgo/smarttrader/core.py
meridianalgo/smarttrader/gpu.py
meridianalgo/smarttrader/models.py
meridianalgo_smarttrader-1.0.0.dist-info/licenses/LICENSE
meridianalgo_smarttrader-1.0.0.dist-info/METADATA
meridianalgo_smarttrader-1.0.0.dist-info/WHEEL
meridianalgo_smarttrader-1.0.0.dist-info/entry_points.txt
meridianalgo_smarttrader-1.0.0.dist-info/top_level.txt
meridianalgo_smarttrader-1.0.0.dist-info/RECORD
