Metadata-Version: 2.4
Name: meridianalgo-smarttrader
Version: 1.0.0
Summary: Ultra-Accurate AI Stock Analysis with Universal GPU Support (AMD • Intel • NVIDIA • Apple)
Home-page: https://github.com/MeridianAlgo/In-Python
Author: MeridianAlgo
Author-email: MeridianAlgo <contact@meridianalgo.com>
Maintainer-email: MeridianAlgo <contact@meridianalgo.com>
License: MIT
Project-URL: Homepage, https://github.com/MeridianAlgo/smart-trader
Project-URL: Documentation, https://github.com/MeridianAlgo/smart-trader/blob/main/README.md
Project-URL: Repository, https://github.com/MeridianAlgo/smart-trader.git
Project-URL: Bug Tracker, https://github.com/MeridianAlgo/smart-trader/issues
Project-URL: Changelog, https://github.com/MeridianAlgo/smart-trader/blob/main/CHANGELOG.md
Project-URL: PyPI, https://pypi.org/project/meridianalgo-smarttrader/
Keywords: stock-analysis,ai,machine-learning,trading,finance,gpu,amd,nvidia,intel,apple-silicon,pytorch,ensemble-learning,volatility,technical-analysis,predictions
Classifier: Development Status :: 5 - Production/Stable
Classifier: Intended Audience :: Financial and Insurance Industry
Classifier: Intended Audience :: Developers
Classifier: Topic :: Office/Business :: Financial :: Investment
Classifier: Topic :: Scientific/Engineering :: Artificial Intelligence
Classifier: License :: OSI Approved :: MIT License
Classifier: Programming Language :: Python :: 3
Classifier: Programming Language :: Python :: 3.8
Classifier: Programming Language :: Python :: 3.9
Classifier: Programming Language :: Python :: 3.10
Classifier: Programming Language :: Python :: 3.11
Classifier: Programming Language :: Python :: 3.12
Classifier: Programming Language :: Python :: 3.13
Classifier: Operating System :: OS Independent
Classifier: Environment :: GPU :: NVIDIA CUDA
Classifier: Environment :: GPU
Requires-Python: >=3.8
License-File: LICENSE
Requires-Dist: torch>=2.1.0
Requires-Dist: pandas>=2.1.0
Requires-Dist: numpy>=1.24.0
Requires-Dist: scikit-learn>=1.3.0
Requires-Dist: yfinance>=0.2.18
Requires-Dist: matplotlib>=3.7.0
Requires-Dist: seaborn>=0.12.0
Requires-Dist: shap>=0.43.0
Requires-Dist: ta>=0.10.2
Requires-Dist: python-dotenv>=1.0.0
Requires-Dist: requests>=2.31.0
Requires-Dist: psutil>=5.9.0
Requires-Dist: colorama>=0.4.6
Requires-Dist: tabulate>=0.9.0
Requires-Dist: tqdm>=4.66.0
Requires-Dist: joblib>=1.3.0
Requires-Dist: rich>=13.7.0
Provides-Extra: gpu-nvidia
Requires-Dist: torch[cuda]; extra == "gpu-nvidia"
Requires-Dist: torchvision; extra == "gpu-nvidia"
Requires-Dist: torchaudio; extra == "gpu-nvidia"
Provides-Extra: gpu-amd
Requires-Dist: torch-directml; extra == "gpu-amd"
Provides-Extra: gpu-intel
Requires-Dist: intel-extension-for-pytorch; extra == "gpu-intel"
Provides-Extra: dev
Requires-Dist: pytest; extra == "dev"
Requires-Dist: black; extra == "dev"
Requires-Dist: flake8; extra == "dev"
Requires-Dist: mypy; extra == "dev"
Requires-Dist: twine; extra == "dev"
Requires-Dist: build; extra == "dev"
Provides-Extra: all
Requires-Dist: torch[cuda]; extra == "all"
Requires-Dist: torchvision; extra == "all"
Requires-Dist: torchaudio; extra == "all"
Requires-Dist: torch-directml; extra == "all"
Requires-Dist: intel-extension-for-pytorch; extra == "all"
Dynamic: author
Dynamic: home-page
Dynamic: license-file
Dynamic: requires-python
